pydantic_schemaorg/AMRadioChannel.py
pydantic_schemaorg/APIReference.py
pydantic_schemaorg/Abdomen.py
pydantic_schemaorg/AboutPage.py
pydantic_schemaorg/AcceptAction.py
pydantic_schemaorg/Accommodation.py
pydantic_schemaorg/AccountingService.py
pydantic_schemaorg/AchieveAction.py
pydantic_schemaorg/Action.py
pydantic_schemaorg/ActionAccessSpecification.py
pydantic_schemaorg/ActionStatusType.py
pydantic_schemaorg/ActivateAction.py
pydantic_schemaorg/ActivationFee.py
pydantic_schemaorg/ActiveActionStatus.py
pydantic_schemaorg/ActiveNotRecruiting.py
pydantic_schemaorg/AddAction.py
pydantic_schemaorg/AdministrativeArea.py
pydantic_schemaorg/AdultEntertainment.py
pydantic_schemaorg/AdvertiserContentArticle.py
pydantic_schemaorg/AerobicActivity.py
pydantic_schemaorg/AggregateOffer.py
pydantic_schemaorg/AggregateRating.py
pydantic_schemaorg/AgreeAction.py
pydantic_schemaorg/Airline.py
pydantic_schemaorg/Airport.py
pydantic_schemaorg/AlbumRelease.py
pydantic_schemaorg/AlignmentObject.py
pydantic_schemaorg/AllWheelDriveConfiguration.py
pydantic_schemaorg/AllergiesHealthAspect.py
pydantic_schemaorg/AllocateAction.py
pydantic_schemaorg/AmpStory.py
pydantic_schemaorg/AmusementPark.py
pydantic_schemaorg/AnaerobicActivity.py
pydantic_schemaorg/AnalysisNewsArticle.py
pydantic_schemaorg/AnatomicalStructure.py
pydantic_schemaorg/AnatomicalSystem.py
pydantic_schemaorg/Anesthesia.py
pydantic_schemaorg/AnimalShelter.py
pydantic_schemaorg/Answer.py
pydantic_schemaorg/Apartment.py
pydantic_schemaorg/ApartmentComplex.py
pydantic_schemaorg/Appearance.py
pydantic_schemaorg/AppendAction.py
pydantic_schemaorg/ApplyAction.py
pydantic_schemaorg/ApprovedIndication.py
pydantic_schemaorg/Aquarium.py
pydantic_schemaorg/ArchiveComponent.py
pydantic_schemaorg/ArchiveOrganization.py
pydantic_schemaorg/ArriveAction.py
pydantic_schemaorg/ArtGallery.py
pydantic_schemaorg/Artery.py
pydantic_schemaorg/Article.py
pydantic_schemaorg/AskAction.py
pydantic_schemaorg/AskPublicNewsArticle.py
pydantic_schemaorg-1.0.6.dist-info/LICENSE.md
pydantic_schemaorg-1.0.6.dist-info/WHEEL
pydantic_schemaorg-1.0.6.dist-info/METADATA
pydantic_schemaorg-1.0.6.dist-info/RECORD
